Metadata-Version: 2.1
Name: sidpy
Version: 0.12.8
Summary: Python utilities for storing, visualizing, and processing Spectroscopic and Imaging Data (SID)
Home-page: https://pycroscopy.github.io/sidpy/about.html
Author: Pycroscopy contributors
Author-email: pycroscopy@gmail.com
License: MIT
Keywords: imaging,spectra,multidimensional,scientific,visualization,processing,storage,hdf5
Platform: Linux
Platform: Mac OSX
Platform: Windows 11/10
Classifier: Development Status :: 2 - Pre-Alpha
Classifier: Environment :: Console
Classifier: Intended Audience :: Science/Research
Classifier: License :: OSI Approved :: MIT License
Classifier: Natural Language :: English
Classifier: Operating System :: OS Independent
Classifier: Programming Language :: Cython
Classifier: Programming Language :: Python :: 3
Classifier: Programming Language :: Python :: 3.9
Classifier: Programming Language :: Python :: 3.10
Classifier: Programming Language :: Python :: 3.11
Classifier: Programming Language :: Python :: 3.12
Classifier: Programming Language :: Python :: Implementation :: CPython
Classifier: Topic :: Scientific/Engineering :: Information Analysis
License-File: LICENSE
Requires-Dist: numpy>=1.10
Requires-Dist: toolz
Requires-Dist: cytoolz
Requires-Dist: dask
Requires-Dist: h5py>=2.6.0
Requires-Dist: matplotlib>=2.0.0
Requires-Dist: distributed>=2.0.0
Requires-Dist: six
Requires-Dist: joblib>=0.11.0
Requires-Dist: ipywidgets
Requires-Dist: ipykernel
Requires-Dist: ipython
Requires-Dist: scikit-learn
Requires-Dist: scipy
Requires-Dist: ase
Requires-Dist: ipympl
Requires-Dist: dill
Provides-Extra: mpi
Requires-Dist: mpi4py; extra == "mpi"
